block_recurrent_transformer_pytorch/__init__.py
block_recurrent_transformer_pytorch/block_recurrent_transformer_pytorch.py
block_recurrent_transformer_pytorch-0.4.4.dist-info/LICENSE
block_recurrent_transformer_pytorch-0.4.4.dist-info/METADATA
block_recurrent_transformer_pytorch-0.4.4.dist-info/WHEEL
block_recurrent_transformer_pytorch-0.4.4.dist-info/top_level.txt
block_recurrent_transformer_pytorch-0.4.4.dist-info/RECORD
