Metadata-Version: 2.1
Name: block-recurrent-transformer-pytorch
Version: 0.4.4
Summary: Block Recurrent Transformer - Pytorch
Home-page: https://github.com/lucidrains/block-recurrent-transformer-pytorch
Author: Phil Wang
Author-email: lucidrains@gmail.com
License: MIT
Keywords: artificial intelligence,deep learning,transformers,attention mechanism,recurrence
Classifier: Development Status :: 4 - Beta
Classifier: Intended Audience :: Developers
Classifier: Topic :: Scientific/Engineering :: Artificial Intelligence
Classifier: License :: OSI Approved :: MIT License
Classifier: Programming Language :: Python :: 3.6
License-File: LICENSE
Requires-Dist: beartype
Requires-Dist: einops >=0.6.1
Requires-Dist: memorizing-transformers-pytorch >=0.4.0
Requires-Dist: torch >=1.6
